[
    {
        "id": 1,
        "link": "https://drive.google.com/file/d/1R-aRE9Ff5pI5dpjj4gYQp7XtqT7oUY5n/view?usp=drive_link",
        "size": "6.01 MB",
        "title": "FT-7023 သုံးထပ်နဘေ (ဓါတ်ဆီ၊ဓါတ်စံ)",
        "type": "mp3"
    },
    {
        "id": 2,
        "link": "https://drive.google.com/file/d/1xjhsQfn3bd2v8pgZX75spQLcVpC0rRci/view?usp=drive_link",
        "size": "6.07 MB",
        "title": "FT-7160 ဖိုးထောင်ဝါနု (ကိုကြင်ခဲ)",
        "type": "mp3"
    },
    {
        "id": 3,
        "link": "https://drive.google.com/file/d/1KcM5ipxnouqdofyI7AWXyQukaVSFW0Rf/view?usp=drive_link",
        "size": "5.92 MB",
        "title": "N-7996 ဗေဒင်ဘိန်းစား (ဓါတ်ဆီ၊ဓါတ်စံ)",
        "type": "mp3"
    },
    {
        "id": 4,
        "link": "https://drive.google.com/file/d/1GOz7gQLVHsRIUEYc9WxZwJrYVawZ5at6/view?usp=drive_link",
        "size": "6.03 MB",
        "title": "N-17521 နောက်ပိုးမျိုးစုံ (ဓါတ်ဆီ၊ဓါတ်စံ)",
        "type": "mp3"
    },
    {
        "id": 5,
        "link": "https://drive.google.com/file/d/1QggDRfbVh5U66G_0FavZUuP2JboEnLqX/view?usp=drive_link",
        "size": "5.57 MB",
        "title": "N-17564 ဣိတ္ထိယစက်ကလေး(၁၂)ပါး (ဓါတ်ဆီ၊ဓါတ်စံ)",
        "type": "mp3"
    },
    {
        "id": 6,
        "link": "https://drive.google.com/file/d/1Wpjld2vehDX8IXKbs2d0ca2OqTx8LYqF/view?usp=drive_link",
        "size": "5.45 MB",
        "title": "N-17594 အမိန့်တော်ပြန်တမ်း (ဓါတ်ဆီ၊ဓါတ်စံ)",
        "type": "mp3"
    },
    {
        "id": 7,
        "link": "https://drive.google.com/file/d/1RIvY4nnOOn3H8BejGSwo0yQlElKU9EfE/view?usp=drive_link",
        "size": "5.69 MB",
        "title": "N-17647 ခင်မောင်စီ (ဓါတ်ဆီ၊ဓါတ်စံ)",
        "type": "mp3"
    },
    {
        "id": 8,
        "link": "https://drive.google.com/file/d/1wbWR7CFaDFZD6iD6DMeM6DuW0N5nz1aE/view?usp=drive_link",
        "size": "10.9 MB",
        "title": "N-17668+1 ကျန်စစ်သား (ဓါတ်ဆီ၊ဓါတ်စံ)",
        "type": "mp3"
    },
    {
        "id": 9,
        "link": "https://drive.google.com/file/d/1K5_u_LjGskGVlBi3-gVaxG1TiDffM6yo/view?usp=drive_link",
        "size": "10.2 MB",
        "title": "N-17679+1 ရေနံချောင်းကဖေကံကောင်း (ဓါတ်ဆီ၊ဓါတ်စံ၊ကိုကြင်ခဲ)",
        "type": "mp3"
    },
    {
        "id": 10,
        "link": "https://drive.google.com/file/d/13cUqgN046sJv3hBV3lUTH6J4_ZV38M6f/view?usp=drive_link",
        "size": "11.0 MB",
        "title": "N-17690+1 ကွက်စိပ် (ဓါတ်ဆီ)",
        "type": "mp3"
    },
    {
        "id": 11,
        "link": "https://drive.google.com/file/d/1q9K0v2vwDIctlI5nN5FNamQo3j1vvUX-/view?usp=drive_link",
        "size": "6.08 MB",
        "title": "N-17702 ကုလားစုံတွဲပျက်လုံး (ဓါတ်ဆီ၊ဓါတ်စံ)",
        "type": "mp3"
    },
    {
        "id": 12,
        "link": "https://drive.google.com/file/d/1X3_Sslqf6t5ohoyoVbSKD0XhzoVmKSO4/view?usp=drive_link",
        "size": "6.10 MB",
        "title": "N-17709 အာဏာရှင် (ဓါတ်ဆီ၊ဓါတ်စံ)_ညီလာခံ",
        "type": "mp3"
    },
    {
        "id": 13,
        "link": "https://drive.google.com/file/d/1G11Zy4WLzi-Yg1FgnGKQWOl6iZcjEqg8/view?usp=drive_link",
        "size": "5.89 MB",
        "title": "N-17726 ရာဇဝင်အူပေါက် (ဓါတ်ဆီ၊ဓါတ်စံ)",
        "type": "mp3"
    },
    {
        "id": 14,
        "link": "https://drive.google.com/file/d/1YNuLlR8YbhehfR0KG5877rLi5Uzr2zEt/view?usp=drive_link",
        "size": "4.66 MB",
        "title": "N-17746 ချီပါသားနဲ့ပခန်းသား (ဓါတ်ဆီ၊ဓါတ်စံ)",
        "type": "mp3"
    },
    {
        "id": 15,
        "link": "https://drive.google.com/file/d/1OgmFbbXD4OSAAcbEj8Q7xDG-WXyT1QZV/view?usp=drive_link",
        "size": "6.29 MB",
        "title": "N-17752 ပဋာစာရီ (ဓါတ်ဆီ၊ဓါတ်စံ)",
        "type": "mp3"
    },
    {
        "id": 16,
        "link": "https://drive.google.com/file/d/1dfmKx7rsKcv8VbYj37ROaI_QzYrx-Ti0/view?usp=drive_link",
        "size": "5.51 MB",
        "title": "N-17757 နောက်ပိုးမီတင် (ဓါတ်ဆီ၊ဓါတ်စံ)",
        "type": "mp3"
    },
    {
        "id": 17,
        "link": "https://drive.google.com/file/d/1zuQ5Gn3J5eprXSPhIIFqgsrPamdxO-E7/view?usp=drive_link",
        "size": "5.49 MB",
        "title": "N-17759 ရှင်လျှင်ရွှေထီး (ဓါတ်ဆီ+)",
        "type": "mp3"
    },
    {
        "id": 18,
        "link": "https://drive.google.com/file/d/1UnCyJ5BrlAzOaGnwrJna6A9fKOQ77YQy/view?usp=drive_link",
        "size": "5.92 MB",
        "title": "N-17773 ကျီးဖို၊ကျီးမ (ဓါတ်ဆီ၊ဓါတ်စံ)",
        "type": "mp3"
    },
    {
        "id": 19,
        "link": "https://drive.google.com/file/d/17o33X9p-KEPitzC-LaA6y2zLkBk4rIW4/view?usp=drive_link",
        "size": "5.89 MB",
        "title": "N-17783 မာဓင်္ဂပျက်လုံး (ဓါတ်ဆီ၊ဓါတ်စံ) ၁",
        "type": "mp3"
    },
    {
        "id": 20,
        "link": "https://drive.google.com/file/d/1u2g3TWYhs6ih7geCf-3gg2jWgs0CYjPL/view?usp=drive_link",
        "size": "6.06 MB",
        "title": "N-17784 မာဓင်္ဂပျက်လုံး (ဓါတ်ဆီ၊ဓါတ်စံ) ၂",
        "type": "mp3"
    },
    {
        "id": 21,
        "link": "https://drive.google.com/file/d/1209vKS8mcJgICuWvH-9T-wxjkTSkIIwB/view?usp=drive_link",
        "size": "5.40 MB",
        "title": "N-17809 လေကြောင်းကာကွယ်ရေး (ဓါတ်ဆီ၊ဓါတ်စံ)",
        "type": "mp3"
    },
    {
        "id": 22,
        "link": "https://drive.google.com/file/d/1AC4PW5uTsy8C9C7vYbVhTw-XSoofTaNc/view?usp=drive_link",
        "size": "5.99 MB",
        "title": "RE-191 ဘုရားတကာကျောင်းတကာပျက်လုံး (ကိုအောင်မောင်း)",
        "type": "mp3"
    },
    {
        "id": 23,
        "link": "https://drive.google.com/file/d/10m2XS9zzsOpTeOH6RjmJHy9vlxF2wPs4/view?usp=drive_link",
        "size": "5.74 MB",
        "title": "RE-206 ချစ်တီးပျက်လုံး (ကိုအောင်မောင်း)",
        "type": "mp3"
    },
    {
        "id": 24,
        "link": "https://drive.google.com/file/d/1ZjdHkbbsf_mlFmGzZE4DNX7MwEWo8J1u/view?usp=drive_link",
        "size": "6.07 MB",
        "title": "RE-248 ကုလားလို(မဆလာ)ပျက်လုံး (ကိုအောင်မောင်း)",
        "type": "mp3"
    },
    {
        "id": 25,
        "link": "https://drive.google.com/file/d/1SIYULmfWshHkrNAcFaWoI68m68byESFf/view?usp=drive_link",
        "size": "6.10 MB",
        "title": "RE-293 စကားထာဝှက်ပျက်လုံး (ကိုအောင်မောင်း)",
        "type": "mp3"
    },
    {
        "id": 26,
        "link": "https://drive.google.com/file/d/1RQZHBLiL03BVWq3LDqluiRgufs_LhjIh/view?usp=drive_link",
        "size": "6.26 MB",
        "title": "RE-298 လောစံနှင့်ရန်ကမ ပျက်လုံး (ဓါတ်စိန်၊ကျီးညို)",
        "type": "mp3"
    },
    {
        "id": 27,
        "link": "https://drive.google.com/file/d/1ylxadZmnHi48kzx6G0BXvUFqtqO2VicW/view?usp=drive_link",
        "size": "5.65 MB",
        "title": "RE-424 ထမင်းကြမ်းပါတီပျက်လုံး (ကျီးညို၊သော်က)",
        "type": "mp3"
    },
    {
        "id": 28,
        "link": "https://drive.google.com/file/d/1pAvalmUAo74MCCjeN4Y_BticY23rvtp_/view?usp=drive_link",
        "size": "5.62 MB",
        "title": "RE-434 ကာလီဒါသစုံတွဲ (ကိုလံဘီယာအဖွဲ့)",
        "type": "mp3"
    },
    {
        "id": 29,
        "link": "https://drive.google.com/file/d/1pmc1CGNslPVCCclSdW5InMLmi66vNgNF/view?usp=drive_link",
        "size": "5.75 MB",
        "title": "RE-488 ပဲသယ်လင်မယား (ကိုလံဘီယာအဖွဲ့)",
        "type": "mp3"
    },
    {
        "id": 30,
        "link": "https://drive.google.com/file/d/1Cdos5GldiCwZzAvGz4u0Fe60bEqkg3Kp/view?usp=drive_link",
        "size": "5.95 MB",
        "title": "RE-534 ဣသီတာလက်သစ် (ကိုကြင်ခဲ)",
        "type": "mp3"
    },
    {
        "id": 31,
        "link": "https://drive.google.com/file/d/1iNXytbB6dxYLQrpzpVDcrh6ivmuJ46Hh/view?usp=drive_link",
        "size": "5.57 MB",
        "title": "RE-564 လန်ဒန်ဘောလယ် (ကိုလံဘီယာအဖွဲ့)",
        "type": "mp3"
    },
    {
        "id": 32,
        "link": "https://drive.google.com/file/d/1-ce1xs3XEoRvt5zHBYxXDuMVScKoD8hb/view?usp=drive_link",
        "size": "6.01 MB",
        "title": "RE-605 ရည်းစားမျှော်လက်သစ် (ကိုလံဘီယာအဖွဲ့)",
        "type": "mp3"
    },
    {
        "id": 33,
        "link": "https://drive.google.com/file/d/11AfgXYICFRzhNA6_rWhTDnvwXKjJO1DI/view?usp=drive_link",
        "size": "5.88 MB",
        "title": "RE-624 ဝိဇ္ဇာညီနောင် (ဥသြဘသောင်၊ကိုကြင်ခဲ)",
        "type": "mp3"
    },
    {
        "id": 34,
        "link": "https://drive.google.com/file/d/1YswSj9YMGtovSb09RzJ3VTk3zlhqMK2T/view?usp=drive_link",
        "size": "6.24 MB",
        "title": "RE-661 တက်ခေတ်သင်္ကြန်စာ (ဥသြဘသောင်၊ကိုကြင်ခဲ)",
        "type": "mp3"
    },
    {
        "id": 35,
        "link": "https://drive.google.com/file/d/1fyVOeaRdQDU58R9Bt0gV2qlZxF9zYTmt/view?usp=drive_link",
        "size": "3.19 MB ",
        "title": "RE-704 ပြောင်းဖူးသယ် (ကိုလံဘီယာအဖွဲ့)",
        "type": "mp3"
    },
    {
        "id": 36,
        "link": "https://drive.google.com/file/d/1Um_drVsWUZU35nb0Q_RS0_pq7sWnnWEf/view?usp=drive_link",
        "size": "2.91 MB",
        "title": "RE-704 အနှိပ်သယ် (ကိုလံဘီယာအဖွဲ့)",
        "type": "mp3"
    },
    {
        "id": 37,
        "link": "https://drive.google.com/file/d/1pqHRsaW-PkqEYE_pOGb6gxHFMLmkOgm1/view?usp=drive_link",
        "size": "5.78 MB",
        "title": "RE-758 ခေတ်သစ်မင်းတိုင်ပင် (ဒန်ပေါက်နှင့်ဓါတ်စိန်)",
        "type": "mp3"
    },
    {
        "id": 38,
        "link": "https://drive.google.com/file/d/1nucsEddjv13hzXqeNlIVJ52yqNg0Rcm1/view?usp=drive_link",
        "size": "6.13 MB",
        "title": "RE-798 ခေတ်ဆန်းသံပေါက် (သူရောင်၊စိတ္တ)",
        "type": "mp3"
    },
    {
        "id": 39,
        "link": "https://drive.google.com/file/d/1tAsxeuVtWjeb503_gynIgCG6EuNq4qNF/view?usp=drive_link",
        "size": "2.98 MB",
        "title": "SG-22 လွတ်တော်အမတ်_မင်းတိုင်ပင် (ဒန်ပေါက်နှင့်ညှပ်ကြီး)",
        "type": "mp3"
    },
    {
        "id": 40,
        "link": "https://drive.google.com/file/d/1dfy7yW87AIITuDjqVTpIHKxa7CuQMUhG/view?usp=drive_link",
        "size": "5.88 MB",
        "title": "TAYOTE THICHIN (KO KYIN KHE",
        "type": "mp3"
    },
    {
        "id": 41,
        "link": "https://drive.google.com/file/d/10t4g4uUf0LY-8cN88O0ohV886fsWVbqW/view?usp=drive_link",
        "size": "6.16 MB",
        "title": "ကာကပျက်လုံး (ဓါတ်စံ၊ကြယ်ပြောင်) ၁",
        "type": "mp3"
    },
    {
        "id": 42,
        "link": "https://drive.google.com/file/d/1C68gxUhF4F9Ko70x2mWL7UsnsuDkN1i3/view?usp=drive_link",
        "size": "6.25 MB",
        "title": "ကာကပျက်လုံး (ဓါတ်စံ၊ကြယ်ပြောင်) ၂",
        "type": "mp3"
    },
    {
        "id": 43,
        "link": "https://drive.google.com/file/d/1ltX9l9d47zy-RkJz29Sbs8J82wcxefN-/view?usp=drive_link",
        "size": "5.89 MB",
        "title": "နှစ်ပါးသွားစုံတွဲ (သြဘာတင်၊မောင်ဓါတ်စံ)",
        "type": "mp3"
    },
    {
        "id": 44,
        "link": "https://drive.google.com/file/d/1pH2V1EliHl07wUrYIhKcBX-HZIRHArTf/view?usp=drive_link",
        "size": "5.92 MB",
        "title": "ပျော်တော်ဆက် (ဒန်ပေါက်နှင့်ညှပ်ကြီး)",
        "type": "mp3"
    },
    {
        "id": 45,
        "link": "https://drive.google.com/file/d/1XJrGJVrk39df-SapKpom1hMvIEtR2CLb/view?usp=drive_link",
        "size": "5.51 MB",
        "title": "ဖားသီချင်း (ကိုကြင်ခဲ)",
        "type": "mp3"
    },
    {
        "id": 46,
        "link": "https://drive.google.com/file/d/1YqUlb0LjO0Zx-HHTZsfJ6p57owrWQb0a/view?usp=drive_link",
        "size": "6.20 MB",
        "title": "ဘောက်သီချင်း (ကိုကြင်ခဲ)",
        "type": "mp3"
    },
    {
        "id": 47,
        "link": "https://drive.google.com/file/d/198zk22nWTQjG9DjxsdBXeaply_8id2X2/view?usp=drive_link",
        "size": "5.95 MB",
        "title": "ရယ်ဘွယ်ပျက်လုံး (ကိုအောင်မောင်း)",
        "type": "mp3"
    },
    {
        "id": 48,
        "link": "https://drive.google.com/file/d/1oUt4OwYhTY4kWKqL1fLiKGxFoTFVOmul/view?usp=drive_link",
        "size": "6.06 MB",
        "title": "ရယ်ရွှင်စရာ (ကိုကြင်ခဲ)",
        "type": "mp3"
    },
    {
        "id": 49,
        "link": "https://drive.google.com/file/d/1YE8LQxff-rQ1W4UkfcJLKDyhNT-023TD/view?usp=drive_link",
        "size": "5.61 MB",
        "title": "သင်္ကြန်စုံတွဲ (မောင်ဓါတ်စိန်၊မညွန့်မေ)",
        "type": "mp3"
    },
    {
        "id": 50,
        "link": "https://drive.google.com/file/d/1k_tV-5sOrdrSnLxLBIm5jzegR4a7wsXt/view?usp=drive_link",
        "size": "5.82 MB ",
        "title": "အိမ်ဆောက်သီချငး် (ကိုကြင်ခဲ)",
        "type": "mp3"
    }
]